{
  "levels": [
    {
      "symbol": "BTC",
      "name": "Bitcoin",
      "current_price": 67673.7,
      "long_liquidations": [
        49955.60904618851,
        56586.24800324064,
        60479.2146636615
      ],
      "short_liquidations": [
        74439.98906421933,
        76021.58750498641,
        84533.21467210766
      ],
      "long_oi": 222.0269910669394,
      "short_oi": 350.2803408171461
    },
    {
      "symbol": "ETH",
      "name": "Ethereum",
      "current_price": 1962.69,
      "long_liquidations": [
        1381.1124622476511,
        1614.6106268320418,
        1812.4090332813562
      ],
      "short_liquidations": [
        2125.249662024804,
        2190.912913366969,
        2311.9632109338363
      ],
      "long_oi": 153.58122015312637,
      "short_oi": 468.6082152256604
    },
    {
      "symbol": "SOL",
      "name": "Solana",
      "current_price": 84.61,
      "long_liquidations": [
        65.4182419729063,
        70.75287247063586,
        77.29771399468966
      ],
      "short_liquidations": [
        91.41955323219564,
        96.4247744962439,
        105.5304263527566
      ],
      "long_oi": 106.95118965034658,
      "short_oi": 211.64474716627456
    },
    {
      "symbol": "BNB",
      "name": "BNB",
      "current_price": 618.49,
      "long_liquidations": [
        433.0027068724534,
        521.2965422222884,
        567.1815140617288
      ],
      "short_liquidations": [
        666.9252791497818,
        690.3549570056713,
        721.8046600047578
      ],
      "long_oi": 111.29231832473377,
      "short_oi": 193.8802941508792
    },
    {
      "symbol": "XRP",
      "name": "XRP",
      "current_price": 1.4318,
      "long_liquidations": [
        1.013512093308916,
        1.2047271055638122,
        1.2244545052406388
      ],
      "short_liquidations": [
        1.5311610537485525,
        1.5991620272505163,
        1.77304483408002
      ],
      "long_oi": 215.31124770352574,
      "short_oi": 291.84962465045464
    },
    {
      "symbol": "ADA",
      "name": "Cardano",
      "current_price": 0.2911,
      "long_liquidations": [
        0.20962550429349597,
        0.23434892372983193,
        0.26595206948615663
      ],
      "short_liquidations": [
        0.3154322563309846,
        0.32037280330890844,
        0.3578072591296921
      ],
      "long_oi": 134.57285890248625,
      "short_oi": 251.65081394815493
    },
    {
      "symbol": "DOGE",
      "name": "Dogecoin",
      "current_price": 0.1018,
      "long_liquidations": [
        0.07491284179224714,
        0.08633481742089065,
        0.08790596659959428
      ],
      "short_liquidations": [
        0.10884608384781598,
        0.11242781442730818,
        0.12700475506533562
      ],
      "long_oi": 481.4501705012052,
      "short_oi": 160.132323828795
    },
    {
      "symbol": "AVAX",
      "name": "Avalanche",
      "current_price": 9.18,
      "long_liquidations": [
        7.178032280470558,
        7.6151023080776135,
        8.243694204534789
      ],
      "short_liquidations": [
        9.809633317390906,
        10.525524493545646,
        10.8766132695948
      ],
      "long_oi": 135.6187022926524,
      "short_oi": 392.21391202679587
    },
    {
      "symbol": "DOT",
      "name": "Polkadot",
      "current_price": 1.355,
      "long_liquidations": [
        0.9628821477883626,
        1.1011736729094874,
        1.2202185195099573
      ],
      "short_liquidations": [
        1.4328403782412145,
        1.5465272035604682,
        1.6599818608976333
      ],
      "long_oi": 122.9514254836582,
      "short_oi": 282.7824354011125
    },
    {
      "symbol": "MATIC",
      "name": "Polygon",
      "current_price": 0.3794,
      "long_liquidations": [
        0.28056891122320676,
        0.317288812037417,
        0.34897314583034483
      ],
      "short_liquidations": [
        0.4143594387992086,
        0.42608981694365045,
        0.46282326166938315
      ],
      "long_oi": 275.7135986859418,
      "short_oi": 323.9979982722934
    }
  ],
  "timestamp": "2026-02-20T16:11:44.791941"
}